dash_table/Format.py
dash_table/FormatTemplate.py
dash_table/__init__.py
dash_table-5.0.0.dist-info/LICENSE
dash_table-5.0.0.dist-info/METADATA
dash_table-5.0.0.dist-info/WHEEL
dash_table-5.0.0.dist-info/top_level.txt
dash_table-5.0.0.dist-info/RECORD
