Metadata-Version: 2.1
Name: dash_table
Version: 5.0.0
Summary: Dash table
Home-page: UNKNOWN
Author: Chris Parmer <chris@plotly.com>
License: MIT
Platform: UNKNOWN
